batchop/__init__.py
batchop/batchop.py
batchop/colors.py
batchop/common.py
batchop/db.py
batchop/english.py
batchop/fileset.py
batchop/filters.py
batchop/globreplace.py
batchop/parsing.py
batchop/patterns.py
batchop-0.1.2.dist-info/METADATA
batchop-0.1.2.dist-info/WHEEL
batchop-0.1.2.dist-info/entry_points.txt
batchop-0.1.2.dist-info/RECORD
