Metadata-Version: 2.1
Name: batchop
Version: 0.1.2
Summary: Batch file operations with an intuitive syntax and safe defaults
Author: Ian Fisher
Author-email: ian@iafisher.com
Requires-Python: >=3.11,<4.0
Classifier: Programming Language :: Python :: 3
Classifier: Programming Language :: Python :: 3.11
Classifier: Programming Language :: Python :: 3.12
